iomete_sdk/api_utils.py
iomete_sdk/security/__init__.py
iomete_sdk/security/data_security.py
iomete_sdk/security/policy_models.py
iomete_sdk/spark/__init__.py
iomete_sdk/spark/spark_job.py
iomete_sdk-3.0.1.dist-info/METADATA
iomete_sdk-3.0.1.dist-info/WHEEL
iomete_sdk-3.0.1.dist-info/top_level.txt
iomete_sdk-3.0.1.dist-info/RECORD
