Metadata-Version: 2.4
Name: iomete_sdk
Version: 3.0.1
Summary: IOMETE SDK for Python.
Home-page: https://github.com/iomete/iomete-sdk
Author: IOMETE
Author-email: vusal@iomete.com
License: Apache License 2.0
Keywords: iomete,sdk,spark-job,data-security-api
Classifier: Development Status :: 5 - Production/Stable
Classifier: Topic :: Software Development :: Build Tools
Classifier: License :: OSI Approved :: Apache Software License
Classifier: Operating System :: Microsoft :: Windows
Classifier: Operating System :: MacOS :: MacOS X
Classifier: Operating System :: POSIX :: Linux
Classifier: Programming Language :: Python :: 3.9
Classifier: Programming Language :: Python :: 3.10
Classifier: Programming Language :: Python :: 3.11
Classifier: Programming Language :: Python :: 3.12
Classifier: Programming Language :: Python :: 3.13
Requires-Python: >=3.9
Requires-Dist: requests==2.32.5
Requires-Dist: dataclasses-json==0.6.7
Provides-Extra: dev
Requires-Dist: pytest; extra == "dev"
Dynamic: author
Dynamic: author-email
Dynamic: classifier
Dynamic: description
Dynamic: description-content-type
Dynamic: home-page
Dynamic: keywords
Dynamic: license
Dynamic: provides-extra
Dynamic: requires-dist
Dynamic: requires-python
Dynamic: summary
